python3_markdown_extension_graphviz/__init__.py
python3_markdown_extension_graphviz/main.py
python3_markdown_extension_graphviz-0.1.0.dist-info/LICENSE
python3_markdown_extension_graphviz-0.1.0.dist-info/WHEEL
python3_markdown_extension_graphviz-0.1.0.dist-info/METADATA
python3_markdown_extension_graphviz-0.1.0.dist-info/RECORD
