Metadata-Version: 2.1
Name: python3-markdown-extension-graphviz
Version: 0.1.0
Summary: 
License: MIT
Author: Manuel Brea
Author-email: m.brea.carreras@gmail.com
Requires-Python: >=3.10,<4.0
Classifier: License :: OSI Approved :: MIT License
Classifier: Programming Language :: Python :: 3
Classifier: Programming Language :: Python :: 3.10
Requires-Dist: Markdown (>=3.4.1,<4.0.0)
